fast_diff_py/__init__.py
fast_diff_py/base_process.py
fast_diff_py/cache.py
fast_diff_py/child_processes.py
fast_diff_py/config.py
fast_diff_py/datatransfer.py
fast_diff_py/dif.py
fast_diff_py/fast_dif.py
fast_diff_py/img_processing.py
fast_diff_py/img_processing_gpu.py
fast_diff_py/main.py
fast_diff_py/sqlite_db.py
fast_diff_py/sqlite_wrapper.py
fast_diff_py/utils.py
fast_diff_py-1.0.4.dist-info/LICENSE.txt
fast_diff_py-1.0.4.dist-info/METADATA
fast_diff_py-1.0.4.dist-info/WHEEL
fast_diff_py-1.0.4.dist-info/entry_points.txt
fast_diff_py-1.0.4.dist-info/RECORD
