Metadata-Version: 2.1
Name: fast-diff-py
Version: 1.0.4
Summary: Multiprocessing implementation of difpy with a focus on performance, disk cache and progress retention.
Home-page: https://github.com/AliSot2000/Fast-Image-Deduplicator
License: MIT
Keywords: python,image deduplicator,fast image deduplicator
Author: AliSot2000
Author-email: alisot200@gmail.com
Requires-Python: >=3.12,<4.0
Classifier: Development Status :: 4 - Beta
Classifier: Intended Audience :: Developers
Classifier: License :: OSI Approved :: MIT License
Classifier: Operating System :: MacOS :: MacOS X
Classifier: Operating System :: Microsoft :: Windows
Classifier: Operating System :: POSIX :: Linux
Classifier: Programming Language :: Python :: 3
Classifier: Programming Language :: Python :: 3.12
Classifier: Programming Language :: Python :: 3.13
Provides-Extra: cuda
Requires-Dist: annotated-types (>=0.7.0,<0.8.0)
Requires-Dist: cupy (>=13.3.0,<14.0.0) ; extra == "cuda"
Requires-Dist: matplotlib (>=3.10.0,<4.0.0)
Requires-Dist: numpy (>=2.2.1,<3.0.0)
Requires-Dist: opencv-python (>=4.10.0.84,<5.0.0.0)
Requires-Dist: pydantic (>=2.10.4,<3.0.0)
Requires-Dist: scikit-image (>=0.25.0,<0.26.0)
Project-URL: Repository, https://github.com/AliSot2000/Fast-Image-Deduplicator
